{
    "assets": {
        "rectangle_image": {"type": "image", "source": "./../Graphics/rectangle.png"},
        "grass_tile_image": {"type": "image", "source": "./../Graphics/grass_tile.png"},
        "male_fighter_spritesheet": {"type": "spritesheet", "source": "./../Graphics/characters/fighter.png", "frame_width": 60, "frame_height": 65},
        "female_mage_spritesheet": {"type": "spritesheet", "source": "./../Graphics/characters/mage.png", "frame_width": 48, "frame_height": 65},
        "bat_spritesheet": {"type": "spritesheet", "source": "./../Graphics/monsters/demonic_essence.png", "frame_width": 128, "frame_height": 128}
    },
    "groups": [
        "background",
        "player_units",
        "enemy_units",
        "hud"
    ],
    "prefabs": {
        "background": {
            "type": "background",
            "position": {"x": 0, "y": 0},
            "properties": {
                "texture": "grass_tile_image",
                "group": "background",
                "width": 320,
                "height": 320
            }
        },
        "enemy_rectangle": {
            "type": "rectangle",
            "position": {"x": 0, "y": 200},
            "properties": {
                "texture": "rectangle_image",
                "group": "hud",
                "scale": {"x": 0.3, "y": 1}
            }
        },
        "action_rectangle": {
            "type": "rectangle",
            "position": {"x": 96, "y": 200},
            "properties": {
                "texture": "rectangle_image",
                "group": "hud",
                "scale": {"x": 0.3, "y": 1}
            }
        },
        "player_rectangle": {
            "type": "rectangle",
            "position": {"x": 192, "y": 200},
            "properties": {
                "texture": "rectangle_image",
                "group": "hud",
                "scale": {"x": 0.4, "y": 1}
            }
        },
        "fighter": {
            "type": "player_unit",
            "position": {"x": 250, "y": 50},
            "properties": {
                "texture": "male_fighter_spritesheet",
                "group": "player_units",
                "frame": 19,
                "stats": {
                    "attack": 15,
                    "defense": 5,
                    "health": 100
                }
            }
        },
        "mage": {
            "type": "player_unit",
            "position": {"x": 250, "y": 150},
            "properties": {
                "texture": "female_mage_spritesheet",
                "group": "player_units",
                "frame": 18,
                "stats": {
                    "attack": 20,
                    "defense": 2,
                    "health": 100
                }
            }
        },
        "boss": {
            "type": "enemy_unit",
            "position": {"x": 100, "y": 90},
            "properties": {
                "texture": "bat_spritesheet",
                "group": "enemy_units",
                "stats": {
                    "attack": 25,
                    "defense": 4,
                    "health": 120
                }
            }
        }
    }
}